bin/linux/mf6
bin/linux/mfnwt
bin/linux/mp6
bin/linux/mp7
bin/linux/mt3dusgs
bin/mac/mf6
bin/mac/mfnwt
bin/mac/mp6
bin/mac/mp7
bin/mac/mt3dusgs
bin/win/mf6.exe
bin/win/mfnwt.exe
bin/win/mp6.exe
bin/win/mp7.exe
bin/win/mt3d-usgs_1.1.0_64.exe
hydromodpy/__init__.py
hydromodpy/watershed_root.py
hydromodpy/display/__init__.py
hydromodpy/display/export_vtuvtk.py
hydromodpy/display/visualization_results.py
hydromodpy/display/visualization_watershed.py
hydromodpy/modeling/__init__.py
hydromodpy/modeling/masstransfer.py
hydromodpy/modeling/modflow.py
hydromodpy/modeling/modpath.py
hydromodpy/modeling/mt3dms.py
hydromodpy/modeling/netcdf.py
hydromodpy/modeling/timeseries.py
hydromodpy/pyhelp/__init__.py
hydromodpy/pyhelp/bilan.py
hydromodpy/pyhelp/daily_output.py
hydromodpy/pyhelp/help_example.py
hydromodpy/pyhelp/help_example_cli.py
hydromodpy/pyhelp/main_cdf.py
hydromodpy/pyhelp/managers.py
hydromodpy/pyhelp/output.py
hydromodpy/pyhelp/prepare_inputs.py
hydromodpy/pyhelp/preprocessing.py
hydromodpy/pyhelp/processing.py
hydromodpy/pyhelp/pyhelp_csv_manager.py
hydromodpy/pyhelp/pyhelp_era5.py
hydromodpy/pyhelp/pyhelp_grid.py
hydromodpy/pyhelp/pyhelp_netcdf.py
hydromodpy/pyhelp/pyhelp_netcdf_writer.py
hydromodpy/pyhelp/utils.py
hydromodpy/pyhelp/weather_reader.py
hydromodpy/tools/__init__.py
hydromodpy/tools/folder_root.py
hydromodpy/tools/log_manager.py
hydromodpy/tools/toolbox.py
hydromodpy/watershed/__init__.py
hydromodpy/watershed/climatic.py
hydromodpy/watershed/driasclimat.py
hydromodpy/watershed/driaseau.py
hydromodpy/watershed/geographic.py
hydromodpy/watershed/geology.py
hydromodpy/watershed/hydraulic.py
hydromodpy/watershed/hydrography.py
hydromodpy/watershed/hydrometry.py
hydromodpy/watershed/intermittency.py
hydromodpy/watershed/oceanic.py
hydromodpy/watershed/piezometry.py
hydromodpy/watershed/safransurfex.py
hydromodpy/watershed/settings.py
hydromodpy/watershed/sim2.py
hydromodpy/watershed/subbasin.py
hydromodpy/watershed/transport.py
hydromodpy-0.3.4.dist-info/licenses/LICENSE
hydromodpy-0.3.4.dist-info/METADATA
hydromodpy-0.3.4.dist-info/WHEEL
hydromodpy-0.3.4.dist-info/top_level.txt
hydromodpy-0.3.4.dist-info/RECORD
