Metadata-Version: 2.4
Name: hydromodpy
Version: 0.3.4
Summary: A Python toolbox for deploying catchment-scale shallow groundwater models
Author-email: Alexandre Gauvain <alexandre.gauvain.ag@gmail.com>, Ronan Abhervé <ronan.abherve@gmail.com>, Jean-Raynald de Dreuzy <jean-raynald.de-dreuzy@univ-rennes.fr>
Maintainer-email: Alexandre Gauvain <alexandre.gauvain.ag@gmail.com>, Ronan Abhervé <ronan.abherve@gmail.com>, Bastien Boivin <bastien.boivin@proton.me>
License-Expression: EPL-2.0
Project-URL: Homepage, https://hydromod.readthedocs.io/
Project-URL: Documentation, https://hydromod.readthedocs.io/
Project-URL: Repository, https://gitlab.com/Alex-Gauvain/HydroModPy
Project-URL: Issues, https://gitlab.com/Alex-Gauvain/HydroModPy/-/issues
Project-URL: Google Group, https://groups.google.com/g/hydromodpy
Keywords: hydrology,hydrogeology,groundwater,modflow,watershed,modeling,catchment
Classifier: Development Status :: 4 - Beta
Classifier: Intended Audience :: Science/Research
Classifier: Operating System :: OS Independent
Classifier: Programming Language :: Python :: 3
Classifier: Programming Language :: Python :: 3.11
Classifier: Programming Language :: Python :: 3.12
Classifier: Programming Language :: Python :: 3.13
Classifier: Topic :: Scientific/Engineering :: Hydrology
Classifier: Topic :: Scientific/Engineering :: GIS
Requires-Python: <3.14,>=3.11
License-File: LICENSE
Requires-Dist: colormap
Requires-Dist: contextily
Requires-Dist: flopy
Requires-Dist: geopandas
Requires-Dist: h5py
Requires-Dist: imageio
Requires-Dist: ipykernel
Requires-Dist: ipython
Requires-Dist: matplotlib
Requires-Dist: matplotlib-scalebar
Requires-Dist: netCDF4
Requires-Dist: numpy>=2.0
Requires-Dist: pandas
Requires-Dist: plotly
Requires-Dist: pyproj
Requires-Dist: pyshp
Requires-Dist: pysheds
Requires-Dist: rasterio
Requires-Dist: rioxarray
Requires-Dist: selenium
Requires-Dist: vedo
Requires-Dist: whitebox
Requires-Dist: xarray
Requires-Dist: pyside6
Requires-Dist: spyder-kernels
Provides-Extra: docs
Requires-Dist: sphinx>=7.0; extra == "docs"
Requires-Dist: sphinx-rtd-theme; extra == "docs"
Requires-Dist: myst-parser; extra == "docs"
Requires-Dist: nbsphinx; extra == "docs"
Requires-Dist: sphinx-gallery; extra == "docs"
Requires-Dist: sphinx-autobuild; extra == "docs"
Requires-Dist: readthedocs-sphinx-ext; extra == "docs"
Requires-Dist: pydata-sphinx-theme; extra == "docs"
Requires-Dist: sphinx-design; extra == "docs"
Requires-Dist: sphinx-copybutton; extra == "docs"
Requires-Dist: sphinx-togglebutton; extra == "docs"
Requires-Dist: sphinx-tabs; extra == "docs"
Requires-Dist: sphinx-multiversion; extra == "docs"
Provides-Extra: ide
Requires-Dist: spyder>=6.0; extra == "ide"
Requires-Dist: jupyterlab>=4.0; extra == "ide"
Dynamic: license-file
